mLab_WalkSpeedRadar/__init__.py
mLab_WalkSpeedRadar/presence_walkSpeed_0.py
mLab_WalkSpeedRadar/walk_speed.py
mLab_WalkSpeed_Radar_Tool-0.0.2.2.dist-info/LICENSE
mLab_WalkSpeed_Radar_Tool-0.0.2.2.dist-info/METADATA
mLab_WalkSpeed_Radar_Tool-0.0.2.2.dist-info/WHEEL
mLab_WalkSpeed_Radar_Tool-0.0.2.2.dist-info/top_level.txt
mLab_WalkSpeed_Radar_Tool-0.0.2.2.dist-info/RECORD
