Metadata-Version: 2.1
Name: mLab-WalkSpeed-Radar-Tool
Version: 0.0.2.2
Summary: mLab WalkSpeed Radar UART tool and example code
Home-page: UNKNOWN
Author: Alex Kuan
Author-email: agathakuannew@gmail.com
License: MIT
Platform: UNKNOWN
Requires-Dist: pyserial
Requires-Dist: pyqtgraph
